atc2txt/__init__.py
atc2txt/_version.py
atc2txt/main.py
atc2txt/lib/__init__.py
atc2txt/lib/client.py
atc2txt/lib/download_model.py
atc2txt/lib/parse_arguments.py
atc2txt/lib/run_client.py
atc2txt/lib/run_server.py
atc2txt/lib/server.py
atc2txt/lib/transcriber.py
atc2txt/lib/utils.py
atc2txt/lib/vad.py
atc2txt-0.6.0.dist-info/LICENSE-CC.txt
atc2txt-0.6.0.dist-info/LICENSE-MIT.txt
atc2txt-0.6.0.dist-info/METADATA
atc2txt-0.6.0.dist-info/WHEEL
atc2txt-0.6.0.dist-info/entry_points.txt
atc2txt-0.6.0.dist-info/top_level.txt
atc2txt-0.6.0.dist-info/RECORD
