Metadata-Version: 2.2
Name: atc2txt
Version: 0.6.0
Summary: Automatic speech recognition and transcription of ATC (Air Traffic Control) streams
Author-email: Jeff Moe <moe@spacecruft.org>
License: MIT
Project-URL: Homepage, https://atc2txt.org
Project-URL: Documentation, https://atc2txt.org
Project-URL: Repository, https://spacecruft.org/aviation/atc2txt
Project-URL: Issues, https://spacecruft.org/aviation/atc2txt
Project-URL: Changelog, https://spacecruft.org/aviation/atc2txt/raw/branch/main/CHANGELOG.txt
Keywords: air-traffic-control,ASR,ATC,automatic-speech-recognition,torch,TTS,txt-to-speech
Classifier: Development Status :: 3 - Alpha
Classifier: Environment :: Console
Classifier: Intended Audience :: Developers
Classifier: License :: OSI Approved :: MIT License
Classifier: Natural Language :: English
Classifier: Operating System :: OS Independent
Classifier: Programming Language :: Python :: 3
Classifier: Topic :: Communications
Classifier: Topic :: Multimedia :: Sound/Audio :: Speech
Classifier: Topic :: Scientific/Engineering :: Artificial Intelligence
Classifier: Topic :: Text Processing :: Linguistic
Requires-Python: >=3.9
License-File: LICENSE-CC.txt
License-File: LICENSE-MIT.txt
Requires-Dist: PyAudio
Requires-Dist: av
Requires-Dist: evaluate
Requires-Dist: faster-whisper==1.1.0
Requires-Dist: jiwer
Requires-Dist: kaldialign
Requires-Dist: numba
Requires-Dist: numpy<2
Requires-Dist: onnxruntime==1.17.0
Requires-Dist: openai-whisper==20240930
Requires-Dist: python-dotenv
Requires-Dist: requests
Requires-Dist: scipy
Requires-Dist: soundfile
Requires-Dist: tokenizers==0.20.3
Requires-Dist: torch
Requires-Dist: websockets
Requires-Dist: websocket-client
Provides-Extra: dev
Requires-Dist: black; extra == "dev"
Requires-Dist: ruff; extra == "dev"
Requires-Dist: setuptools-scm; extra == "dev"
Requires-Dist: sphinx; extra == "dev"
Requires-Dist: sphinx-autobuild; extra == "dev"
Requires-Dist: sphinx-autodoc-typehints; extra == "dev"
Requires-Dist: sphinx-intl; extra == "dev"
Requires-Dist: sphinx-notfound-page; extra == "dev"
Requires-Dist: sphinx-rtd-theme; extra == "dev"
Requires-Dist: sphinxcontrib-markdown; extra == "dev"
Requires-Dist: transpolibre; extra == "dev"
Requires-Dist: twine; extra == "dev"
